README.md
setup.py
src/tf14/__init__.py
src/tf14/api_methods.py
src/tf14/cli.py
src/tf14/cli_utils.py
src/tf14/scripts/apply.sh
src/tf14/scripts/clean.sh
src/tf14/scripts/init.sh
src/tf14/scripts/plan.sh
src/tf14_cli.egg-info/PKG-INFO
src/tf14_cli.egg-info/SOURCES.txt
src/tf14_cli.egg-info/dependency_links.txt
src/tf14_cli.egg-info/entry_points.txt
src/tf14_cli.egg-info/requires.txt
src/tf14_cli.egg-info/top_level.txt